colormylogs/main.py
colormylogs-0.4.0.dist-info/METADATA
colormylogs-0.4.0.dist-info/WHEEL
colormylogs-0.4.0.dist-info/entry_points.txt
colormylogs-0.4.0.dist-info/top_level.txt
colormylogs-0.4.0.dist-info/RECORD
