Metadata-Version: 2.2
Name: colormylogs
Version: 0.4.0
Requires-Python: >=3.12
Requires-Dist: rich>=13.9.4
Requires-Dist: typer>=0.15.1
